pda/constants.py
pda/src/data.py
ariel_pda-0.1.0.dist-info/METADATA
ariel_pda-0.1.0.dist-info/WHEEL
ariel_pda-0.1.0.dist-info/RECORD
