Metadata-Version: 2.1
Name: ariel_pda
Version: 0.1.0
Summary: 
Author: RArielAlonso
Author-email: rariel.alonso@gmail.com
Requires-Python: >=3.8,<4.0
Classifier: Programming Language :: Python :: 3
Classifier: Programming Language :: Python :: 3.8
Classifier: Programming Language :: Python :: 3.9
Classifier: Programming Language :: Python :: 3.10
Classifier: Programming Language :: Python :: 3.11
Requires-Dist: pandas (>=2.0,<3.0)
